gem-migrator
setup.cfg
setup.py
gem_migrator/__init__.py
gem_migrator/nacl_passphrasebox.py
gem_migrator.egg-info/PKG-INFO
gem_migrator.egg-info/SOURCES.txt
gem_migrator.egg-info/dependency_links.txt
gem_migrator.egg-info/not-zip-safe
gem_migrator.egg-info/requires.txt
gem_migrator.egg-info/top_level.txt