Metadata-Version: 1.0
Name: gem-migrator
Version: 0.1.5
Summary: utility for migrating Gem application wallets
Home-page: http://github.com/GemHQ/gem-migrator
Author: Matt Smith
Author-email: matt@gem.co
License: MIT
Platform: UNKNOWN
